{"lastUsed":1684049708773,"path":"\/home\/lord448\/Escritorio\/STM32Workspaces\/Practicas_SO_Embebidos","projectCount":5,"recentFiles":[{"path":"\/Plot_current\/USB_DEVICE\/App","parentWorkspace":"\/home\/lord448\/Escritorio\/STM32Workspaces\/Practicas_SO_Embebidos","name":"usbd_cdc_if.h","lastModified":1684044268895,"locationURI":"file:\/home\/lord448\/Escritorio\/STM32Workspaces\/Practicas_SO_Embebidos\/Plot_current\/USB_DEVICE\/App\/usbd_cdc_if.h"},{"path":"\/Plot_current\/USB_DEVICE\/App","parentWorkspace":"\/home\/lord448\/Escritorio\/STM32Workspaces\/Practicas_SO_Embebidos","name":"usbd_cdc_if.c","lastModified":1684044310967,"locationURI":"file:\/home\/lord448\/Escritorio\/STM32Workspaces\/Practicas_SO_Embebidos\/Plot_current\/USB_DEVICE\/App\/usbd_cdc_if.c"},{"path":"\/Plot_current\/Middlewares\/Third_Party\/FreeRTOS\/Source\/CMSIS_RTOS_V2","parentWorkspace":"\/home\/lord448\/Escritorio\/STM32Workspaces\/Practicas_SO_Embebidos","name":"cmsis_os2.c","lastModified":1684037796790,"locationURI":"file:\/home\/lord448\/Escritorio\/STM32Workspaces\/Practicas_SO_Embebidos\/Plot_current\/Middlewares\/Third_Party\/FreeRTOS\/Source\/CMSIS_RTOS_V2\/cmsis_os2.c"},{"path":"\/Control_Plot\/USB_DEVICE\/App","parentWorkspace":"\/home\/lord448\/Escritorio\/STM32Workspaces\/Practicas_SO_Embebidos","name":"usbd_cdc_if.h","lastModified":1684049532628,"locationURI":"file:\/home\/lord448\/Escritorio\/STM32Workspaces\/Practicas_SO_Embebidos\/Control_Plot\/USB_DEVICE\/App\/usbd_cdc_if.h"},{"path":"\/Control_Plot\/USB_DEVICE\/App","parentWorkspace":"\/home\/lord448\/Escritorio\/STM32Workspaces\/Practicas_SO_Embebidos","name":"usbd_cdc_if.c","lastModified":1684049499939,"locationURI":"file:\/home\/lord448\/Escritorio\/STM32Workspaces\/Practicas_SO_Embebidos\/Control_Plot\/USB_DEVICE\/App\/usbd_cdc_if.c"},{"path":"\/Plot_current\/Core\/Src","parentWorkspace":"\/home\/lord448\/Escritorio\/STM32Workspaces\/Practicas_SO_Embebidos","name":"main.c","lastModified":1684046156124,"locationURI":"file:\/home\/lord448\/Escritorio\/STM32Workspaces\/Practicas_SO_Embebidos\/Plot_current\/Core\/Src\/main.c"},{"path":"\/Plot_current","parentWorkspace":"\/home\/lord448\/Escritorio\/STM32Workspaces\/Practicas_SO_Embebidos","name":"Plot_current.ioc","lastModified":1684046179239,"locationURI":"file:\/home\/lord448\/Escritorio\/STM32Workspaces\/Practicas_SO_Embebidos\/Plot_current\/Plot_current.ioc"},{"path":"\/Plot_current\/USB_DEVICE\/Target","parentWorkspace":"\/home\/lord448\/Escritorio\/STM32Workspaces\/Practicas_SO_Embebidos","name":"usbd_conf.c","lastModified":1684044447187,"locationURI":"file:\/home\/lord448\/Escritorio\/STM32Workspaces\/Practicas_SO_Embebidos\/Plot_current\/USB_DEVICE\/Target\/usbd_conf.c"},{"path":"\/Control_Plot","parentWorkspace":"\/home\/lord448\/Escritorio\/STM32Workspaces\/Practicas_SO_Embebidos","name":"Control_Plot.ioc","lastModified":1684047020307,"locationURI":"file:\/home\/lord448\/Escritorio\/STM32Workspaces\/Practicas_SO_Embebidos\/Control_Plot\/Control_Plot.ioc"},{"path":"\/Control_Plot\/Core\/Src","parentWorkspace":"\/home\/lord448\/Escritorio\/STM32Workspaces\/Practicas_SO_Embebidos","name":"main.c","lastModified":1684049657850,"locationURI":"file:\/home\/lord448\/Escritorio\/STM32Workspaces\/Practicas_SO_Embebidos\/Control_Plot\/Core\/Src\/main.c"}]}